sftp_client/__init__.py
sftp_client/exceptions.py
sftp_client/drivers/__init__.py
sftp_client/drivers/base.py
sftp_client/drivers/chilkat_client.py
sftp_client/drivers/pexpect_client.py
sftp_client-1.0.4.dist-info/DESCRIPTION.rst
sftp_client-1.0.4.dist-info/METADATA
sftp_client-1.0.4.dist-info/RECORD
sftp_client-1.0.4.dist-info/WHEEL
sftp_client-1.0.4.dist-info/metadata.json
sftp_client-1.0.4.dist-info/top_level.txt
