Metadata-Version: 2.0
Name: sftp-client
Version: 1.0.4
Summary: An API to make SFTP file transfers through chilkat simpler and more pythonic
Home-page: https://github.com/TheKewlStore/PySFTPClient
Author: Ian Davis
Author-email: thekewlstore@gmail.com
License: UNKNOWN
Platform: UNKNOWN
Requires-Dist: unit-conversion
